MoodleQuizParser/QuizParser.py
MoodleQuizParser/__init__.py
MoodleQuizParser/Models/Answer.py
MoodleQuizParser/Models/ChoiceAnswer.py
MoodleQuizParser/Models/MatchingAnswer.py
MoodleQuizParser/Models/Question.py
MoodleQuizParser/Models/TextAnswer.py
MoodleQuizParser/Models/__init__.py
py_moodle_quiz_parser-0.0.6.dist-info/LICENSE
py_moodle_quiz_parser-0.0.6.dist-info/METADATA
py_moodle_quiz_parser-0.0.6.dist-info/WHEEL
py_moodle_quiz_parser-0.0.6.dist-info/top_level.txt
py_moodle_quiz_parser-0.0.6.dist-info/RECORD
