Metadata-Version: 2.1
Name: py-moodle-quiz-parser
Version: 0.0.6
Summary: Package for parsing moodle quiz HTML documents
Home-page: https://github.com/Kononenko-Daniil/py-moodle-quiz-parser
Author: Daniil Kononenko
License: MIT
Project-URL: Documentation, https://py-moodle-quiz-parser.readthedocs.io/en/latest/
Project-URL: Source, https://github.com/Kononenko-Daniil/py-moodle-quiz-parser
License-File: LICENSE
Requires-Dist: beautifulsoup4
